lora_pro/__init__.py
lora_pro/_lorapro.py
lora_pro/adamw.py
lora_pro_adamw-0.2.1.dist-info/METADATA
lora_pro_adamw-0.2.1.dist-info/WHEEL
lora_pro_adamw-0.2.1.dist-info/licenses/LICENSE
lora_pro_adamw-0.2.1.dist-info/RECORD
