Metadata-Version: 2.4
Name: lora-pro-adamw
Version: 0.2.1
Summary: LoRA-Pro gradient-corrected AdamW optimizer for PyTorch and PEFT
Project-URL: Homepage, https://github.com/bamps53/lora-pro-adamw
Project-URL: Repository, https://github.com/bamps53/lora-pro-adamw
Project-URL: Issues, https://github.com/bamps53/lora-pro-adamw/issues
Author: Daisuke Yamamoto
License: MIT
License-File: LICENSE
Keywords: LoRA,lora-pro,optimizer,pytorch
Classifier: Programming Language :: Python :: 3
Classifier: Programming Language :: Python :: 3.11
Classifier: Topic :: Scientific/Engineering :: Artificial Intelligence
Requires-Python: >=3.11
Requires-Dist: peft>=0.17.1
Requires-Dist: torch>=2.4.0
Provides-Extra: dev
Requires-Dist: hatch>=1.9.0; extra == 'dev'
Requires-Dist: pytest>=8.4.2; extra == 'dev'
